[
    [
        {
            "author": "廿廿呀",
            "title": "和女机长的畸形网恋",
            "url": "https://www.jjwxc.net/onebook.php?novelid=7759944",
            "genre": "近代现代-爱情",
            "status": "连载",
            "wordCount": "378873字",
            "credits": "335,482,016",
            "latestUpdates": "2025-01-10 01:04:53"
        },
        {
            "author": "胡33",
            "title": "我的哑巴新娘",
            "url": "https://www.jjwxc.net/onebook.php?novelid=9220117",
            "genre": "架空历史-爱情",
            "status": "连载",
            "wordCount": "273330字",
            "credits": "176,778,912",
            "latestUpdates": "2025-01-09 20:58:13"
        },
        {
            "author": "秦淮洲",
            "title": "会员日",
            "url": "https://www.jjwxc.net/onebook.php?novelid=9245277",
            "genre": "近代现代-爱情",
            "status": "连载",
            "wordCount": "96647字",
            "credits": "164,158,880",
            "latestUpdates": "2025-01-09 22:35:53"
        },
        {
            "author": "唐九书",
            "title": "大佬A说孩子是她的",
            "url": "https://www.jjwxc.net/onebook.php?novelid=7905046",
            "genre": "近代现代-爱情",
            "status": "连载",
            "wordCount": "337280字",
            "credits": "76,417,856",
            "latestUpdates": "2025-01-08 23:00:00"
        },
        {
            "author": "两点一现",
            "title": "和不回家的大佬结婚后",
            "url": "https://www.jjwxc.net/onebook.php?novelid=8896846",
            "genre": "近代现代-爱情",
            "status": "连载",
            "wordCount": "284316字",
            "credits": "40,911,620",
            "latestUpdates": "2025-01-09 23:35:04"
        },
        {
            "author": "江湘西岸",
            "title": "欺负小哑巴的一百零八式",
            "url": "https://www.jjwxc.net/onebook.php?novelid=9308089",
            "genre": "近代现代-爱情",
            "status": "连载",
            "wordCount": "218068字",
            "credits": "40,553,652",
            "latestUpdates": "2025-01-09 22:18:49"
        },
        {
            "author": "一个白羊",
            "title": "私有姐姐",
            "url": "https://www.jjwxc.net/onebook.php?novelid=8877212",
            "genre": "近代现代-爱情",
            "status": "连载",
            "wordCount": "45151字",
            "credits": "29,821,260",
            "latestUpdates": "2025-01-09 02:44:56"
        },
        {
            "author": "泗亦",
            "title": "误标记了继妹的白月光后",
            "url": "https://www.jjwxc.net/onebook.php?novelid=9177066",
            "genre": "近代现代-爱情",
            "status": "连载",
            "wordCount": "146289字",
            "credits": "26,717,852",
            "latestUpdates": "2025-01-10 01:12:22"
        },
        {
            "author": "湮秋",
            "title": "我想救救她",
            "url": "https://www.jjwxc.net/onebook.php?novelid=7744135",
            "genre": "近代现代-爱情",
            "status": "连载",
            "wordCount": "61917字",
            "credits": "24,725,392",
            "latestUpdates": "2024-11-27 23:55:49"
        },
        {
            "author": "艾叶英",
            "title": "谢天谢地你来了",
            "url": "https://www.jjwxc.net/onebook.php?novelid=8835072",
            "genre": "近代现代-爱情",
            "status": "连载",
            "wordCount": "260191字",
            "credits": "17,463,414",
            "latestUpdates": "2025-01-09 21:01:03"
        },
        {
            "author": "我我我心匪石",
            "title": "替身她骗了大佬身心后跑了",
            "url": "https://www.jjwxc.net/onebook.php?novelid=8480077",
            "genre": "近代现代-爱情",
            "status": "连载",
            "wordCount": "75986字",
            "credits": "17,328,836",
            "latestUpdates": "2025-01-08 21:05:12"
        },
        {
            "author": "鲸岛阿眠",
            "title": "被清冷霸总掰弯后",
            "url": "https://www.jjwxc.net/onebook.php?novelid=9275770",
            "genre": "近代现代-爱情",
            "status": "连载",
            "wordCount": "215678字",
            "credits": "15,265,048",
            "latestUpdates": "2025-01-10 00:30:12"
        },
        {
            "author": "成禹锦",
            "title": "高冷A她在偷偷暗恋我",
            "url": "https://www.jjwxc.net/onebook.php?novelid=9117487",
            "genre": "近代现代-爱情",
            "status": "完结",
            "wordCount": "109281字",
            "credits": "8,222,124",
            "latestUpdates": "2025-01-05 17:05:36"
        },
        {
            "author": "树海C",
            "title": "洛川寻故人",
            "url": "https://www.jjwxc.net/onebook.php?novelid=9291682",
            "genre": "架空历史-仙侠",
            "status": "连载",
            "wordCount": "182300字",
            "credits": "6,620,918",
            "latestUpdates": "2025-01-09 23:41:31"
        },
        {
            "author": "鸡毛令箭",
            "title": "意外成抛妻弃女的渣女了",
            "url": "https://www.jjwxc.net/onebook.php?novelid=9270883",
            "genre": "近代现代-爱情",
            "status": "连载",
            "wordCount": "10142字",
            "credits": "6,597,284",
            "latestUpdates": "2024-11-09 11:00:00"
        },
        {
            "author": "天土八月",
            "title": "消渴",
            "url": "https://www.jjwxc.net/onebook.php?novelid=8943862",
            "genre": "近代现代-爱情",
            "status": "连载",
            "wordCount": "145049字",
            "credits": "6,147,267",
            "latestUpdates": "2025-01-09 23:26:13"
        },
        {
            "author": "江山河",
            "title": "祸水与美人",
            "url": "https://www.jjwxc.net/onebook.php?novelid=6171443",
            "genre": "近代现代-爱情",
            "status": "连载",
            "wordCount": "82800字",
            "credits": "5,914,624",
            "latestUpdates": "2025-01-09 19:00:15"
        },
        {
            "author": "Somna",
            "title": "失忆后去追了死对头A",
            "url": "https://www.jjwxc.net/onebook.php?novelid=8473101",
            "genre": "近代现代-爱情",
            "status": "连载",
            "wordCount": "18666字",
            "credits": "5,905,579",
            "latestUpdates": "2025-01-07 22:16:00"
        },
        {
            "author": "筌檫檫",
            "title": "都是直女，亲亲咋了",
            "url": "https://www.jjwxc.net/onebook.php?novelid=9063030",
            "genre": "近代现代-爱情",
            "status": "连载",
            "wordCount": "65231字",
            "credits": "4,877,519",
            "latestUpdates": "2025-01-09 22:50:19"
        },
        {
            "author": "侍清镜",
            "title": "呆呆同桌逆天改命",
            "url": "https://www.jjwxc.net/onebook.php?novelid=8839350",
            "genre": "近代现代-爱情",
            "status": "连载",
            "wordCount": "198401字",
            "credits": "4,676,227",
            "latestUpdates": "2024-12-26 18:00:58"
        },
        {
            "author": "烛狗蛋",
            "title": "亲吻左耳",
            "url": "https://www.jjwxc.net/onebook.php?novelid=9301609",
            "genre": "近代现代-爱情",
            "status": "连载",
            "wordCount": "83406字",
            "credits": "4,648,712",
            "latestUpdates": "2025-01-02 19:58:46"
        },
        {
            "author": "入于",
            "title": "日与月同耀gl",
            "url": "https://www.jjwxc.net/onebook.php?novelid=8494090",
            "genre": "近代现代-爱情",
            "status": "连载",
            "wordCount": "143030字",
            "credits": "4,370,437",
            "latestUpdates": "2025-01-08 23:12:53"
        },
        {
            "author": "屯屯怪",
            "title": "哭包师姐为我偏执了",
            "url": "https://www.jjwxc.net/onebook.php?novelid=9322524",
            "genre": "架空历史-爱情",
            "status": "连载",
            "wordCount": "72456字",
            "credits": "3,494,094",
            "latestUpdates": "2025-01-09 02:00:05"
        },
        {
            "author": "于禅",
            "title": "捡的狼崽对我情根深种",
            "url": "https://www.jjwxc.net/onebook.php?novelid=8880737",
            "genre": "近代现代-爱情",
            "status": "连载",
            "wordCount": "42605字",
            "credits": "3,004,214",
            "latestUpdates": "2024-12-10 13:37:56"
        },
        {
            "author": "爱吃橘子的橙子",
            "title": "催眠女主？大小姐要改变BE结局",
            "url": "https://www.jjwxc.net/onebook.php?novelid=9214349",
            "genre": "近代现代-爱情",
            "status": "连载",
            "wordCount": "43978字",
            "credits": "2,891,880",
            "latestUpdates": "2024-11-10 23:45:47"
        },
        {
            "author": "林平江",
            "title": "年下递来恋爱合约",
            "url": "https://www.jjwxc.net/onebook.php?novelid=8802881",
            "genre": "近代现代-爱情",
            "status": "连载",
            "wordCount": "58677字",
            "credits": "2,850,836",
            "latestUpdates": "2024-12-10 23:12:04"
        },
        {
            "author": "姀晚",
            "title": "姗岚可依",
            "url": "https://www.jjwxc.net/onebook.php?novelid=9319875",
            "genre": "架空历史-爱情",
            "status": "连载",
            "wordCount": "111972字",
            "credits": "2,518,067",
            "latestUpdates": "2025-01-09 22:50:40"
        },
        {
            "author": "坐在村口胡说八道",
            "title": "原身归来！恶毒女配创飞所有人",
            "url": "https://www.jjwxc.net/onebook.php?novelid=9312324",
            "genre": "近代现代-爱情",
            "status": "连载",
            "wordCount": "65449字",
            "credits": "2,514,364",
            "latestUpdates": "2024-12-13 18:18:18"
        },
        {
            "author": "长夜一灯明",
            "title": "白月光回来倒追我了",
            "url": "https://www.jjwxc.net/onebook.php?novelid=9254026",
            "genre": "近代现代-爱情",
            "status": "连载",
            "wordCount": "62892字",
            "credits": "1,955,655",
            "latestUpdates": "2025-01-09 01:10:58"
        },
        {
            "author": "采叁秀",
            "title": "温柔校医竟有另一面",
            "url": "https://www.jjwxc.net/onebook.php?novelid=9314349",
            "genre": "近代现代-爱情",
            "status": "完结",
            "wordCount": "45972字",
            "credits": "1,481,136",
            "latestUpdates": "2024-12-26 14:26:45"
        },
        {
            "author": "太古季叶人",
            "title": "尹剑仙，爱上自己",
            "url": "https://www.jjwxc.net/onebook.php?novelid=8080928",
            "genre": "近代现代-爱情",
            "status": "完结",
            "wordCount": "45961字",
            "credits": "1,422,129",
            "latestUpdates": "2024-12-25 21:00:00"
        },
        {
            "author": "元景",
            "title": "傍上朱雀祝统后她拯救世界了",
            "url": "https://www.jjwxc.net/onebook.php?novelid=9334774",
            "genre": "架空历史-剧情",
            "status": "连载",
            "wordCount": "32189字",
            "credits": "1,354,465",
            "latestUpdates": "2024-12-17 20:39:32"
        },
        {
            "author": "酸奶圆子",
            "title": "白月光会自己上钩",
            "url": "https://www.jjwxc.net/onebook.php?novelid=9083536",
            "genre": "近代现代-爱情",
            "status": "连载",
            "wordCount": "142517字",
            "credits": "1,209,721",
            "latestUpdates": "2025-01-09 18:00:16"
        },
        {
            "author": "虎皮炸蛋儿",
            "title": "开门啊我送外卖的",
            "url": "https://www.jjwxc.net/onebook.php?novelid=9327871",
            "genre": "近代现代-爱情",
            "status": "连载",
            "wordCount": "91116字",
            "credits": "794,282",
            "latestUpdates": "2025-01-08 21:50:49"
        },
        {
            "author": "珍珠云",
            "title": "与海有关",
            "url": "https://www.jjwxc.net/onebook.php?novelid=9309234",
            "genre": "近代现代-爱情",
            "status": "完结",
            "wordCount": "152109字",
            "credits": "675,177",
            "latestUpdates": "2024-12-26 19:54:35"
        },
        {
            "author": "四只碗",
            "title": "最是仓皇辞庙日",
            "url": "https://www.jjwxc.net/onebook.php?novelid=9167262",
            "genre": "古色古香-爱情",
            "status": "完结",
            "wordCount": "46345字",
            "credits": "646,294",
            "latestUpdates": "2024-11-22 22:40:47"
        },
        {
            "author": "余笙序",
            "title": "南屏钟声晚",
            "url": "https://www.jjwxc.net/onebook.php?novelid=9310094",
            "genre": "近代现代-爱情",
            "status": "连载",
            "wordCount": "35243字",
            "credits": "605,406",
            "latestUpdates": "2024-12-21 23:00:00"
        },
        {
            "author": "汴兰亭",
            "title": "雪落下的声音",
            "url": "https://www.jjwxc.net/onebook.php?novelid=8718527",
            "genre": "近代现代-爱情",
            "status": "连载",
            "wordCount": "90814字",
            "credits": "533,715",
            "latestUpdates": "2025-01-04 16:57:57"
        },
        {
            "author": "月光陷阱",
            "title": "叒被绿茶学妹缠上了",
            "url": "https://www.jjwxc.net/onebook.php?novelid=9327140",
            "genre": "近代现代-爱情",
            "status": "连载",
            "wordCount": "32824字",
            "credits": "378,892",
            "latestUpdates": "2024-12-20 20:03:48"
        },
        {
            "author": "酒林玉",
            "title": "前任她哭唧唧的",
            "url": "https://www.jjwxc.net/onebook.php?novelid=9251334",
            "genre": "近代现代-爱情",
            "status": "连载",
            "wordCount": "66029字",
            "credits": "369,200",
            "latestUpdates": "2024-11-20 23:03:22"
        },
        {
            "author": "三木已再春",
            "title": "日月合璧",
            "url": "https://www.jjwxc.net/onebook.php?novelid=9256186",
            "genre": "架空历史-剧情",
            "status": "连载",
            "wordCount": "29295字",
            "credits": "318,419",
            "latestUpdates": "2024-12-29 05:41:51"
        },
        {
            "author": "昼时月",
            "title": "今岁忽已晚",
            "url": "https://www.jjwxc.net/onebook.php?novelid=9321320",
            "genre": "架空历史-爱情",
            "status": "连载",
            "wordCount": "64652字",
            "credits": "261,055",
            "latestUpdates": "2025-01-09 21:40:05"
        },
        {
            "author": "洋葱蛋糕",
            "title": "大小姐又要和我玩游戏",
            "url": "https://www.jjwxc.net/onebook.php?novelid=9351412",
            "genre": "近代现代-爱情",
            "status": "连载",
            "wordCount": "32088字",
            "credits": "185,638",
            "latestUpdates": "2025-01-06 15:18:56"
        },
        {
            "author": "鱼刺不会痛",
            "title": "每天都好讨厌她gl",
            "url": "https://www.jjwxc.net/onebook.php?novelid=9296347",
            "genre": "近代现代-剧情",
            "status": "连载",
            "wordCount": "35939字",
            "credits": "154,486",
            "latestUpdates": "2024-12-27 21:56:55"
        },
        {
            "author": "骑着扫把驾驾驾",
            "title": "不散的宴席",
            "url": "https://www.jjwxc.net/onebook.php?novelid=9352874",
            "genre": "近代现代-爱情",
            "status": "连载",
            "wordCount": "35072字",
            "credits": "135,213",
            "latestUpdates": "2024-12-23 20:28:05"
        },
        {
            "author": "渝夜",
            "title": "月沉星隐",
            "url": "https://www.jjwxc.net/onebook.php?novelid=9261326",
            "genre": "近代现代-爱情",
            "status": "连载",
            "wordCount": "46622字",
            "credits": "108,096",
            "latestUpdates": "2024-11-23 14:29:19"
        },
        {
            "author": "安沫妤",
            "title": "浴光",
            "url": "https://www.jjwxc.net/onebook.php?novelid=9288581",
            "genre": "近代现代-爱情",
            "status": "连载",
            "wordCount": "24504字",
            "credits": "106,003",
            "latestUpdates": "2024-12-24 16:33:00"
        },
        {
            "author": "雪雾无尘",
            "title": "纠缠",
            "url": "https://www.jjwxc.net/onebook.php?novelid=9298372",
            "genre": "近代现代-爱情",
            "status": "连载",
            "wordCount": "20468字",
            "credits": "98,956",
            "latestUpdates": "2024-11-21 21:00:00"
        },
        {
            "author": "九訄",
            "title": "吟卿遇",
            "url": "https://www.jjwxc.net/onebook.php?novelid=9245331",
            "genre": "架空历史-仙侠",
            "status": "连载",
            "wordCount": "10053字",
            "credits": "90,059",
            "latestUpdates": "2025-01-09 23:57:07"
        },
        {
            "author": "洛清予",
            "title": "今宵别墨涵",
            "url": "https://www.jjwxc.net/onebook.php?novelid=9288634",
            "genre": "近代现代-爱情",
            "status": "连载",
            "wordCount": "45666字",
            "credits": "87,898",
            "latestUpdates": "2024-11-16 09:41:55"
        },
        {
            "author": "看看我的类别",
            "title": "与死对头的恋爱记录",
            "url": "https://www.jjwxc.net/onebook.php?novelid=9288961",
            "genre": "近代现代-爱情",
            "status": "连载",
            "wordCount": "25784字",
            "credits": "81,875",
            "latestUpdates": "2024-11-15 20:13:42"
        },
        {
            "author": "野火不烬",
            "title": "惊鸿",
            "url": "https://www.jjwxc.net/onebook.php?novelid=9350878",
            "genre": "近代现代-剧情",
            "status": "连载",
            "wordCount": "25506字",
            "credits": "79,627",
            "latestUpdates": "2024-12-16 21:55:25"
        },
        {
            "author": "类鸦",
            "title": "一剑速通权谋局指南",
            "url": "https://www.jjwxc.net/onebook.php?novelid=8868404",
            "genre": "架空历史-仙侠",
            "status": "连载",
            "wordCount": "19154字",
            "credits": "76,975",
            "latestUpdates": "2024-11-08 21:00:00"
        },
        {
            "author": "拉半仙",
            "title": "未居者",
            "url": "https://www.jjwxc.net/onebook.php?novelid=8338489",
            "genre": "近代现代-爱情",
            "status": "连载",
            "wordCount": "12369字",
            "credits": "76,129",
            "latestUpdates": "2025-01-01 00:00:00"
        },
        {
            "author": "游遨",
            "title": "什么喜欢不喜欢",
            "url": "https://www.jjwxc.net/onebook.php?novelid=9265222",
            "genre": "近代现代-爱情",
            "status": "连载",
            "wordCount": "20304字",
            "credits": "68,265",
            "latestUpdates": "2024-10-30 16:31:21"
        },
        {
            "author": "秋素星华",
            "title": "双星",
            "url": "https://www.jjwxc.net/onebook.php?novelid=9242456",
            "genre": "近代现代-爱情",
            "status": "连载",
            "wordCount": "16347字",
            "credits": "62,295",
            "latestUpdates": "2024-10-21 23:59:05"
        },
        {
            "author": "春秋宁晚",
            "title": "她的白月光",
            "url": "https://www.jjwxc.net/onebook.php?novelid=9267581",
            "genre": "近代现代-爱情",
            "status": "连载",
            "wordCount": "10237字",
            "credits": "57,900",
            "latestUpdates": "2024-11-11 21:01:50"
        },
        {
            "author": "并而为徽",
            "title": "高岭之花与空心人",
            "url": "https://www.jjwxc.net/onebook.php?novelid=9310837",
            "genre": "近代现代-爱情",
            "status": "连载",
            "wordCount": "27289字",
            "credits": "56,272",
            "latestUpdates": "2024-11-23 17:13:24"
        },
        {
            "author": "冬枝槐",
            "title": "戴老师答应我le",
            "url": "https://www.jjwxc.net/onebook.php?novelid=9309125",
            "genre": "近代现代-爱情",
            "status": "连载",
            "wordCount": "10538字",
            "credits": "53,841",
            "latestUpdates": "2024-11-26 22:03:11"
        },
        {
            "author": "沐月檀",
            "title": "暖枫下的月光",
            "url": "https://www.jjwxc.net/onebook.php?novelid=9252733",
            "genre": "近代现代-爱情",
            "status": "连载",
            "wordCount": "12509字",
            "credits": "52,469",
            "latestUpdates": "2024-10-25 18:00:05"
        },
        {
            "author": "Yimmune",
            "title": "今夜岛上无雨",
            "url": "https://www.jjwxc.net/onebook.php?novelid=9316556",
            "genre": "近代现代-爱情",
            "status": "连载",
            "wordCount": "26979字",
            "credits": "49,662",
            "latestUpdates": "2024-12-05 21:00:00"
        },
        {
            "author": "淮浮生",
            "title": "时间向我",
            "url": "https://www.jjwxc.net/onebook.php?novelid=9251077",
            "genre": "近代现代-爱情",
            "status": "连载",
            "wordCount": "17009字",
            "credits": "44,451",
            "latestUpdates": "2024-11-19 00:45:09"
        },
        {
            "author": "仙灵梦羽",
            "title": "《双姝仙途：情定九天》",
            "url": "https://www.jjwxc.net/onebook.php?novelid=9350275",
            "genre": "架空历史-仙侠",
            "status": "连载",
            "wordCount": "19171字",
            "credits": "44,075",
            "latestUpdates": "2024-12-31 18:15:04"
        },
        {
            "author": "竹弈风诲",
            "title": "寻生",
            "url": "https://www.jjwxc.net/onebook.php?novelid=8954966",
            "genre": "古色古香-爱情",
            "status": "连载",
            "wordCount": "21673字",
            "credits": "37,026",
            "latestUpdates": "2025-01-06 04:25:17"
        }
    ],
    "2025-01-10, 08:40:30 GMT+8"
]