[
    [
        {
            "author": "圆圈儿",
            "title": "这个反派归我了[快穿]",
            "url": "https://www.jjwxc.net/onebook.php?novelid=7298618",
            "genre": "近代现代-爱情",
            "status": "连载",
            "wordCount": "290357字",
            "credits": "133,300,112",
            "latestUpdates": "2024-04-19 13:12:01"
        },
        {
            "author": "沉睡僵尸",
            "title": "我装的但她真疯[快穿]",
            "url": "https://www.jjwxc.net/onebook.php?novelid=8694254",
            "genre": "近代现代-爱情",
            "status": "连载",
            "wordCount": "302200字",
            "credits": "133,078,312",
            "latestUpdates": "2024-04-19 21:15:01"
        },
        {
            "author": "饭三碗",
            "title": "救赎反派后，被攻略了[快穿]",
            "url": "https://www.jjwxc.net/onebook.php?novelid=6751720",
            "genre": "近代现代-爱情",
            "status": "连载",
            "wordCount": "233887字",
            "credits": "119,200,312",
            "latestUpdates": "2024-04-19 18:00:30"
        },
        {
            "author": "或许有一天",
            "title": "带着淘宝去复国",
            "url": "https://www.jjwxc.net/onebook.php?novelid=7574183",
            "genre": "架空历史-爱情",
            "status": "连载",
            "wordCount": "114215字",
            "credits": "45,958,000",
            "latestUpdates": "2024-04-19 18:27:14"
        },
        {
            "author": "三木成深",
            "title": "疯娇O和她的百万金丝雀",
            "url": "https://www.jjwxc.net/onebook.php?novelid=8727153",
            "genre": "近代现代-爱情",
            "status": "连载",
            "wordCount": "185621字",
            "credits": "36,040,728",
            "latestUpdates": "2024-04-19 20:00:45"
        },
        {
            "author": "来个上上签",
            "title": "作恶多年，归来仍是恶女[快穿]",
            "url": "https://www.jjwxc.net/onebook.php?novelid=7483779",
            "genre": "近代现代-爱情",
            "status": "连载",
            "wordCount": "225766字",
            "credits": "33,121,956",
            "latestUpdates": "2024-04-19 18:00:00"
        },
        {
            "author": "子非鱼非子",
            "title": "玄学大佬的原配夫人之路",
            "url": "https://www.jjwxc.net/onebook.php?novelid=8505545",
            "genre": "近代现代-爱情",
            "status": "连载",
            "wordCount": "233588字",
            "credits": "29,773,906",
            "latestUpdates": "2024-04-19 09:03:00"
        },
        {
            "author": "尔迩",
            "title": "渣炮灰逆袭后有老婆了[快穿]",
            "url": "https://www.jjwxc.net/onebook.php?novelid=8687644",
            "genre": "近代现代-爱情",
            "status": "连载",
            "wordCount": "203601字",
            "credits": "25,098,972",
            "latestUpdates": "2024-04-18 14:01:36"
        },
        {
            "author": "有鹤啄鱼",
            "title": "她有病［快穿］",
            "url": "https://www.jjwxc.net/onebook.php?novelid=8654890",
            "genre": "幻想未来-爱情",
            "status": "连载",
            "wordCount": "74672字",
            "credits": "24,497,610",
            "latestUpdates": "2024-03-31 23:00:08"
        },
        {
            "author": "再来两坛酒",
            "title": "捡来的霸总O跑了",
            "url": "https://www.jjwxc.net/onebook.php?novelid=8441583",
            "genre": "近代现代-爱情",
            "status": "连载",
            "wordCount": "215083字",
            "credits": "21,034,584",
            "latestUpdates": "2024-04-18 23:41:33"
        },
        {
            "author": "虚空神使",
            "title": "咸鱼被老板读心后躺赢了",
            "url": "https://www.jjwxc.net/onebook.php?novelid=8694409",
            "genre": "近代现代-爱情",
            "status": "连载",
            "wordCount": "197449字",
            "credits": "18,273,068",
            "latestUpdates": "2024-04-18 23:57:38"
        },
        {
            "author": "芝麻酱拌枇杷",
            "title": "女配她深陷修罗场［快穿］",
            "url": "https://www.jjwxc.net/onebook.php?novelid=8718150",
            "genre": "近代现代-爱情",
            "status": "连载",
            "wordCount": "121650字",
            "credits": "17,768,876",
            "latestUpdates": "2024-04-17 22:40:05"
        },
        {
            "author": "桃汁祭酒",
            "title": "拯救悲情女配（快穿）",
            "url": "https://www.jjwxc.net/onebook.php?novelid=8402035",
            "genre": "架空历史-爱情",
            "status": "连载",
            "wordCount": "192350字",
            "credits": "14,315,383",
            "latestUpdates": "2024-04-19 16:08:06"
        },
        {
            "author": "乌九丁",
            "title": "又被女配黏上了[快穿]",
            "url": "https://www.jjwxc.net/onebook.php?novelid=7736363",
            "genre": "近代现代-爱情",
            "status": "连载",
            "wordCount": "110277字",
            "credits": "14,172,809",
            "latestUpdates": "2024-04-19 18:48:27"
        },
        {
            "author": "江映初",
            "title": "攻略反派女二之后",
            "url": "https://www.jjwxc.net/onebook.php?novelid=8014586",
            "genre": "架空历史-爱情",
            "status": "连载",
            "wordCount": "80250字",
            "credits": "13,055,261",
            "latestUpdates": "2024-04-19 06:51:34"
        },
        {
            "author": "牧酒",
            "title": "神明她初来乍到",
            "url": "https://www.jjwxc.net/onebook.php?novelid=5433576",
            "genre": "架空历史-传奇",
            "status": "连载",
            "wordCount": "135462字",
            "credits": "12,746,704",
            "latestUpdates": "2024-04-18 20:07:24"
        },
        {
            "author": "墨洗羽",
            "title": "戏精爆改恋爱脑[快穿]",
            "url": "https://www.jjwxc.net/onebook.php?novelid=3470726",
            "genre": "架空历史-爱情",
            "status": "连载",
            "wordCount": "42509字",
            "credits": "12,727,922",
            "latestUpdates": "2024-04-17 00:40:29"
        },
        {
            "author": "遇星川",
            "title": "先和老婆贴贴[快穿]",
            "url": "https://www.jjwxc.net/onebook.php?novelid=5762897",
            "genre": "近代现代-爱情",
            "status": "连载",
            "wordCount": "60407字",
            "credits": "12,597,365",
            "latestUpdates": "2024-03-20 22:37:54"
        },
        {
            "author": "赐鲤",
            "title": "女主，别撩了[快穿]",
            "url": "https://www.jjwxc.net/onebook.php?novelid=8745347",
            "genre": "近代现代-爱情",
            "status": "连载",
            "wordCount": "140023字",
            "credits": "12,458,542",
            "latestUpdates": "2024-04-19 21:00:00"
        },
        {
            "author": "霜雪一城",
            "title": "是食神不是战神",
            "url": "https://www.jjwxc.net/onebook.php?novelid=8338756",
            "genre": "架空历史-爱情",
            "status": "连载",
            "wordCount": "136034字",
            "credits": "11,291,994",
            "latestUpdates": "2024-04-19 12:00:00"
        },
        {
            "author": "异映七海",
            "title": "疯美反派O没我不行",
            "url": "https://www.jjwxc.net/onebook.php?novelid=8633327",
            "genre": "近代现代-爱情",
            "status": "连载",
            "wordCount": "184433字",
            "credits": "10,846,630",
            "latestUpdates": "2024-04-19 20:00:00"
        },
        {
            "author": "媂元清",
            "title": "攻略反派，屡败屡战",
            "url": "https://www.jjwxc.net/onebook.php?novelid=8563313",
            "genre": "架空历史-爱情",
            "status": "连载",
            "wordCount": "162667字",
            "credits": "10,742,885",
            "latestUpdates": "2024-04-19 06:00:00"
        },
        {
            "author": "觉觉饭饭",
            "title": "女主像鬼一样缠着我[快穿]",
            "url": "https://www.jjwxc.net/onebook.php?novelid=8429154",
            "genre": "近代现代-爱情",
            "status": "连载",
            "wordCount": "79336字",
            "credits": "9,502,537",
            "latestUpdates": "2024-04-14 23:19:18"
        },
        {
            "author": "十三月夜Y",
            "title": "绑定渣攻系统后［快穿］",
            "url": "https://www.jjwxc.net/onebook.php?novelid=8529591",
            "genre": "近代现代-爱情",
            "status": "连载",
            "wordCount": "129333字",
            "credits": "7,239,152",
            "latestUpdates": "2024-04-18 06:57:54"
        },
        {
            "author": "爪子喵",
            "title": "我老婆有病（快穿）",
            "url": "https://www.jjwxc.net/onebook.php?novelid=8363910",
            "genre": "幻想未来-爱情",
            "status": "连载",
            "wordCount": "86332字",
            "credits": "6,521,578",
            "latestUpdates": "2024-04-19 19:21:59"
        },
        {
            "author": "洛生歌",
            "title": "拯救BE游戏女主(快穿)",
            "url": "https://www.jjwxc.net/onebook.php?novelid=8634479",
            "genre": "幻想未来-爱情",
            "status": "连载",
            "wordCount": "113285字",
            "credits": "6,493,488",
            "latestUpdates": "2024-04-19 18:00:00"
        },
        {
            "author": "吹空调的风狗",
            "title": "穿成了女主的灵宠",
            "url": "https://www.jjwxc.net/onebook.php?novelid=8757387",
            "genre": "架空历史-仙侠",
            "status": "连载",
            "wordCount": "83264字",
            "credits": "4,988,697",
            "latestUpdates": "2024-04-01 18:51:55"
        },
        {
            "author": "千尾糕",
            "title": "恶毒女配O她娇又软",
            "url": "https://www.jjwxc.net/onebook.php?novelid=8755527",
            "genre": "近代现代-爱情",
            "status": "连载",
            "wordCount": "65530字",
            "credits": "4,022,600",
            "latestUpdates": "2024-04-18 17:36:42"
        },
        {
            "author": "月晦潮汐",
            "title": "瑶月寄我",
            "url": "https://www.jjwxc.net/onebook.php?novelid=8702349",
            "genre": "架空历史-仙侠",
            "status": "连载",
            "wordCount": "141308字",
            "credits": "1,399,422",
            "latestUpdates": "2024-04-15 06:00:00"
        },
        {
            "author": "炸土豆球",
            "title": "穿成游戏中的反派大Boss怎么办",
            "url": "https://www.jjwxc.net/onebook.php?novelid=8638265",
            "genre": "架空历史-奇幻",
            "status": "连载",
            "wordCount": "66827字",
            "credits": "798,700",
            "latestUpdates": "2024-04-13 12:12:46"
        },
        {
            "author": "椰丝霏霏",
            "title": "遗世",
            "url": "https://www.jjwxc.net/onebook.php?novelid=8662332",
            "genre": "架空历史-爱情",
            "status": "连载",
            "wordCount": "74242字",
            "credits": "715,092",
            "latestUpdates": "2024-04-10 19:24:37"
        },
        {
            "author": "应约以白",
            "title": "我不想攻略我害怕的东西【快穿】",
            "url": "https://www.jjwxc.net/onebook.php?novelid=8631094",
            "genre": "架空历史-爱情",
            "status": "连载",
            "wordCount": "26818字",
            "credits": "519,204",
            "latestUpdates": "2024-04-17 13:11:01"
        },
        {
            "author": "与君同饮",
            "title": "又被反派关小黑屋了[快穿]",
            "url": "https://www.jjwxc.net/onebook.php?novelid=8630386",
            "genre": "架空历史-爱情",
            "status": "连载",
            "wordCount": "13608字",
            "credits": "366,770",
            "latestUpdates": "2024-03-16 12:23:36"
        },
        {
            "author": "噢不乖",
            "title": "攻略我的端王老婆",
            "url": "https://www.jjwxc.net/onebook.php?novelid=7755876",
            "genre": "近代现代-爱情",
            "status": "连载",
            "wordCount": "33772字",
            "credits": "307,675",
            "latestUpdates": "2024-03-23 03:00:00"
        },
        {
            "author": "凉不亮",
            "title": "成为她的遥不可及后",
            "url": "https://www.jjwxc.net/onebook.php?novelid=8766176",
            "genre": "近代现代-爱情",
            "status": "连载",
            "wordCount": "43571字",
            "credits": "307,653",
            "latestUpdates": "2024-04-15 22:13:48"
        },
        {
            "author": "醉暮复朝",
            "title": "怨箫狂剑",
            "url": "https://www.jjwxc.net/onebook.php?novelid=8650236",
            "genre": "架空历史-仙侠",
            "status": "连载",
            "wordCount": "32455字",
            "credits": "262,128",
            "latestUpdates": "2024-02-19 03:00:01"
        },
        {
            "author": "可颂面包",
            "title": "穿书后义妹说要攻略我",
            "url": "https://www.jjwxc.net/onebook.php?novelid=8700036",
            "genre": "架空历史-爱情",
            "status": "连载",
            "wordCount": "29790字",
            "credits": "249,160",
            "latestUpdates": "2024-04-14 19:27:57"
        },
        {
            "author": "不悔入华夏",
            "title": "论在玛丽苏学院赚取生命值",
            "url": "https://www.jjwxc.net/onebook.php?novelid=8726749",
            "genre": "架空历史-剧情",
            "status": "连载",
            "wordCount": "37829字",
            "credits": "208,705",
            "latestUpdates": "2024-03-25 08:00:00"
        },
        {
            "author": "开心的一天",
            "title": "绑定反内卷系统后我躺平了",
            "url": "https://www.jjwxc.net/onebook.php?novelid=8765828",
            "genre": "架空历史-仙侠",
            "status": "连载",
            "wordCount": "21412字",
            "credits": "184,331",
            "latestUpdates": "2024-03-19 00:58:14"
        },
        {
            "author": "少乌长鸦",
            "title": "穿进狗血文做女主的思想启蒙导师",
            "url": "https://www.jjwxc.net/onebook.php?novelid=8654815",
            "genre": "近代现代-爱情",
            "status": "连载",
            "wordCount": "13261字",
            "credits": "160,320",
            "latestUpdates": "2024-02-23 18:36:11"
        },
        {
            "author": "内卷所有人",
            "title": "绑定反内卷系统后我躺平了",
            "url": "https://www.jjwxc.net/onebook.php?novelid=8759972",
            "genre": "架空历史-爱情",
            "status": "连载",
            "wordCount": "17873字",
            "credits": "157,924",
            "latestUpdates": "2024-03-16 14:58:38"
        },
        {
            "author": "咘咘忠犬",
            "title": "当瞎了的我拿了隐忍反叛剧本",
            "url": "https://www.jjwxc.net/onebook.php?novelid=8704502",
            "genre": "近代现代-爱情",
            "status": "连载",
            "wordCount": "10079字",
            "credits": "141,611",
            "latestUpdates": "2024-02-20 17:00:00"
        },
        {
            "author": "在下长生诀",
            "title": "快穿之攻略杀星",
            "url": "https://www.jjwxc.net/onebook.php?novelid=8642906",
            "genre": "架空历史-剧情",
            "status": "连载",
            "wordCount": "21751字",
            "credits": "127,043",
            "latestUpdates": "2024-04-18 19:46:52"
        },
        {
            "author": "枧岁",
            "title": "摆烂后，师姐深情且专一",
            "url": "https://www.jjwxc.net/onebook.php?novelid=8768666",
            "genre": "架空历史-仙侠",
            "status": "连载",
            "wordCount": "20616字",
            "credits": "124,776",
            "latestUpdates": "2024-03-22 16:42:09"
        },
        {
            "author": "觅莱",
            "title": "快穿之山海异兽",
            "url": "https://www.jjwxc.net/onebook.php?novelid=8682881",
            "genre": "架空历史-爱情",
            "status": "连载",
            "wordCount": "20097字",
            "credits": "121,273",
            "latestUpdates": "2024-04-18 00:08:11"
        },
        {
            "author": "不是中二的年纪",
            "title": "女主非说我是她的良人",
            "url": "https://www.jjwxc.net/onebook.php?novelid=8643957",
            "genre": "近代现代-爱情",
            "status": "连载",
            "wordCount": "21829字",
            "credits": "109,750",
            "latestUpdates": "2024-01-29 17:02:30"
        },
        {
            "author": "山雀坠毁",
            "title": "小行星会救地球吗",
            "url": "https://www.jjwxc.net/onebook.php?novelid=8640981",
            "genre": "近代现代-爱情",
            "status": "连载",
            "wordCount": "11585字",
            "credits": "101,249",
            "latestUpdates": "2024-02-15 19:45:59"
        },
        {
            "author": "墨当",
            "title": "被我攻略的男主好像是女生",
            "url": "https://www.jjwxc.net/onebook.php?novelid=8734984",
            "genre": "近代现代-爱情",
            "status": "连载",
            "wordCount": "10647字",
            "credits": "97,339",
            "latestUpdates": "2024-03-06 11:52:48"
        },
        {
            "author": "残词消酒",
            "title": "这无脑虐文女主我不当了",
            "url": "https://www.jjwxc.net/onebook.php?novelid=8747393",
            "genre": "架空历史-爱情",
            "status": "连载",
            "wordCount": "14307字",
            "credits": "96,440",
            "latestUpdates": "2024-04-05 01:52:09"
        },
        {
            "author": "接骨木花",
            "title": "重生后教女帝打乒乓",
            "url": "https://www.jjwxc.net/onebook.php?novelid=8674047",
            "genre": "架空历史-剧情",
            "status": "连载",
            "wordCount": "11406字",
            "credits": "95,810",
            "latestUpdates": "2024-02-06 02:14:54"
        },
        {
            "author": "奕君曦",
            "title": "霸道反派爱上我",
            "url": "https://www.jjwxc.net/onebook.php?novelid=8768836",
            "genre": "近代现代-爱情",
            "status": "连载",
            "wordCount": "10308字",
            "credits": "92,263",
            "latestUpdates": "2024-04-07 18:54:27"
        },
        {
            "author": "抢风",
            "title": "女配何苦为难女配",
            "url": "https://www.jjwxc.net/onebook.php?novelid=8666584",
            "genre": "近代现代-爱情",
            "status": "连载",
            "wordCount": "11034字",
            "credits": "90,512",
            "latestUpdates": "2024-03-26 19:44:06"
        },
        {
            "author": "无菌产品",
            "title": "以前，以后",
            "url": "https://www.jjwxc.net/onebook.php?novelid=8691714",
            "genre": "架空历史-爱情",
            "status": "连载",
            "wordCount": "12383字",
            "credits": "88,189",
            "latestUpdates": "2024-02-18 22:55:02"
        },
        {
            "author": "版蓝根",
            "title": "我和偶像一起穿越了，她居然说我是她的初恋？！",
            "url": "https://www.jjwxc.net/onebook.php?novelid=8714899",
            "genre": "架空历史-爱情",
            "status": "连载",
            "wordCount": "10090字",
            "credits": "77,572",
            "latestUpdates": "2024-03-08 20:59:08"
        },
        {
            "author": "坡县犊子",
            "title": "我为未来的自己操碎了心",
            "url": "https://www.jjwxc.net/onebook.php?novelid=8721838",
            "genre": "近代现代-爱情",
            "status": "连载",
            "wordCount": "14992字",
            "credits": "76,316",
            "latestUpdates": "2024-04-19 00:24:56"
        },
        {
            "author": "倦了人间",
            "title": "玉兰烟雨过春秋",
            "url": "https://www.jjwxc.net/onebook.php?novelid=8707809",
            "genre": "架空历史-剧情",
            "status": "连载",
            "wordCount": "10991字",
            "credits": "42,574",
            "latestUpdates": "2024-02-19 17:08:50"
        }
    ],
    "2024-04-19, 21:22:16 GMT+8"
]