[
    [
        {
            "author": "鲸汣",
            "title": "被献祭给疯批长公主冲喜后",
            "url": "https://www.jjwxc.net/onebook.php?novelid=6364022",
            "genre": "架空历史-爱情",
            "status": "连载",
            "wordCount": "315464字",
            "credits": "280,650,592",
            "latestUpdates": "2024-10-11 02:56:25"
        },
        {
            "author": "昨夜未归",
            "title": "折相让我还她名声",
            "url": "https://www.jjwxc.net/onebook.php?novelid=9011483",
            "genre": "架空历史-爱情",
            "status": "连载",
            "wordCount": "46668字",
            "credits": "69,319,728",
            "latestUpdates": "2024-10-10 18:00:00"
        },
        {
            "author": "千岁一时",
            "title": "续写女主角",
            "url": "https://www.jjwxc.net/onebook.php?novelid=8997339",
            "genre": "近代现代-爱情",
            "status": "连载",
            "wordCount": "257690字",
            "credits": "60,020,240",
            "latestUpdates": "2024-10-10 23:41:45"
        },
        {
            "author": "云荒北城",
            "title": "婚后心动gl[重生]",
            "url": "https://www.jjwxc.net/onebook.php?novelid=4983255",
            "genre": "近代现代-爱情",
            "status": "连载",
            "wordCount": "210474字",
            "credits": "32,511,564",
            "latestUpdates": "2024-10-09 23:00:30"
        },
        {
            "author": "摇叁",
            "title": "钓系装乖，嫂子要弯",
            "url": "https://www.jjwxc.net/onebook.php?novelid=8940926",
            "genre": "近代现代-爱情",
            "status": "连载",
            "wordCount": "57347字",
            "credits": "20,469,732",
            "latestUpdates": "2024-10-09 21:15:00"
        },
        {
            "author": "原味奶酪棒",
            "title": "路人A赘入豪门后",
            "url": "https://www.jjwxc.net/onebook.php?novelid=8431523",
            "genre": "近代现代-爱情",
            "status": "连载",
            "wordCount": "109265字",
            "credits": "15,598,638",
            "latestUpdates": "2024-10-10 09:00:00"
        },
        {
            "author": "赐鲤",
            "title": "满级魔尊开小号[重生]",
            "url": "https://www.jjwxc.net/onebook.php?novelid=8399213",
            "genre": "架空历史-爱情",
            "status": "连载",
            "wordCount": "262663字",
            "credits": "15,597,340",
            "latestUpdates": "2024-10-10 21:00:00"
        },
        {
            "author": "千草成汤",
            "title": "虐文女主A是女配的金丝雀",
            "url": "https://www.jjwxc.net/onebook.php?novelid=9037457",
            "genre": "近代现代-爱情",
            "status": "连载",
            "wordCount": "102225字",
            "credits": "12,037,809",
            "latestUpdates": "2024-10-10 18:00:00"
        },
        {
            "author": "谨奚",
            "title": "闪婚妻子她又美又强",
            "url": "https://www.jjwxc.net/onebook.php?novelid=8876386",
            "genre": "近代现代-爱情",
            "status": "连载",
            "wordCount": "87891字",
            "credits": "9,286,468",
            "latestUpdates": "2024-10-09 16:04:33"
        },
        {
            "author": "甜口山楂",
            "title": "不完美情人[娱乐圈]",
            "url": "https://www.jjwxc.net/onebook.php?novelid=8994970",
            "genre": "近代现代-剧情",
            "status": "连载",
            "wordCount": "117147字",
            "credits": "6,774,224",
            "latestUpdates": "2024-10-09 09:38:59"
        },
        {
            "author": "别学天坑",
            "title": "师妹别修仙了，搞钱",
            "url": "https://www.jjwxc.net/onebook.php?novelid=9101308",
            "genre": "架空历史-仙侠",
            "status": "连载",
            "wordCount": "99564字",
            "credits": "6,028,604",
            "latestUpdates": "2024-10-08 23:00:00"
        },
        {
            "author": "呜呀哇拉",
            "title": "小姐，恋爱脑万万不可！",
            "url": "https://www.jjwxc.net/onebook.php?novelid=9171642",
            "genre": "近代现代-爱情",
            "status": "连载",
            "wordCount": "96193字",
            "credits": "5,812,191",
            "latestUpdates": "2024-10-10 23:51:02"
        },
        {
            "author": "陆谦",
            "title": "被影后拐去荒野求生后红了",
            "url": "https://www.jjwxc.net/onebook.php?novelid=9149990",
            "genre": "近代现代-爱情",
            "status": "连载",
            "wordCount": "104805字",
            "credits": "4,676,896",
            "latestUpdates": "2024-10-08 23:36:48"
        },
        {
            "author": "成禹锦",
            "title": "不准磕我和死对头的同人文",
            "url": "https://www.jjwxc.net/onebook.php?novelid=9110183",
            "genre": "近代现代-爱情",
            "status": "完结",
            "wordCount": "94569字",
            "credits": "4,571,880",
            "latestUpdates": "2024-10-11 00:40:16"
        },
        {
            "author": "厌仙缘",
            "title": "空",
            "url": "https://www.jjwxc.net/onebook.php?novelid=9003751",
            "genre": "近代现代-爱情",
            "status": "连载",
            "wordCount": "135717字",
            "credits": "3,852,564",
            "latestUpdates": "2024-10-07 19:29:02"
        },
        {
            "author": "北离南笙",
            "title": "为你撑伞［单元文］",
            "url": "https://www.jjwxc.net/onebook.php?novelid=8512084",
            "genre": "近代现代-爱情",
            "status": "连载",
            "wordCount": "96526字",
            "credits": "3,697,384",
            "latestUpdates": "2024-10-09 23:00:00"
        },
        {
            "author": "木木很多树",
            "title": "【短篇】心有微澜",
            "url": "https://www.jjwxc.net/onebook.php?novelid=9140681",
            "genre": "架空历史-爱情",
            "status": "完结",
            "wordCount": "40187字",
            "credits": "3,186,148",
            "latestUpdates": "2024-09-13 13:53:20"
        },
        {
            "author": "鱼之漫",
            "title": "朝日照北林",
            "url": "https://www.jjwxc.net/onebook.php?novelid=7952236",
            "genre": "近代现代-爱情",
            "status": "连载",
            "wordCount": "217728字",
            "credits": "2,851,476",
            "latestUpdates": "2024-10-10 01:01:44"
        },
        {
            "author": "燕塞雪",
            "title": "对于女团学我略知一二",
            "url": "https://www.jjwxc.net/onebook.php?novelid=9151439",
            "genre": "近代现代-爱情",
            "status": "连载",
            "wordCount": "108042字",
            "credits": "1,106,659",
            "latestUpdates": "2024-10-10 17:00:00"
        },
        {
            "author": "飞蛾的纠葛",
            "title": "折凛",
            "url": "https://www.jjwxc.net/onebook.php?novelid=9085734",
            "genre": "架空历史-仙侠",
            "status": "连载",
            "wordCount": "120238字",
            "credits": "1,068,901",
            "latestUpdates": "2024-10-10 18:52:04"
        },
        {
            "author": "洛哥儿",
            "title": "不想爱你了",
            "url": "https://www.jjwxc.net/onebook.php?novelid=9134167",
            "genre": "近代现代-爱情",
            "status": "完结",
            "wordCount": "70738字",
            "credits": "907,952",
            "latestUpdates": "2024-09-15 05:05:45"
        },
        {
            "author": "弹射起步",
            "title": "之后",
            "url": "https://www.jjwxc.net/onebook.php?novelid=9166256",
            "genre": "近代现代-爱情",
            "status": "连载",
            "wordCount": "99035字",
            "credits": "658,813",
            "latestUpdates": "2024-10-10 23:38:46"
        },
        {
            "author": "久芷",
            "title": "久久爱",
            "url": "https://www.jjwxc.net/onebook.php?novelid=8928838",
            "genre": "近代现代-爱情",
            "status": "连载",
            "wordCount": "53290字",
            "credits": "527,919",
            "latestUpdates": "2024-10-05 21:58:08"
        },
        {
            "author": "锦喜欢拖更",
            "title": "致我破碎的想念",
            "url": "https://www.jjwxc.net/onebook.php?novelid=9187832",
            "genre": "近代现代-爱情",
            "status": "连载",
            "wordCount": "162616字",
            "credits": "504,256",
            "latestUpdates": "2024-10-11 00:00:00"
        },
        {
            "author": "请不要下雨",
            "title": "成为二五仔后努力自救",
            "url": "https://www.jjwxc.net/onebook.php?novelid=9164156",
            "genre": "架空历史-奇幻",
            "status": "连载",
            "wordCount": "101844字",
            "credits": "489,059",
            "latestUpdates": "2024-10-10 21:45:48"
        },
        {
            "author": "懒酒十三",
            "title": "听说我是亡国公主",
            "url": "https://www.jjwxc.net/onebook.php?novelid=9107239",
            "genre": "架空历史-爱情",
            "status": "连载",
            "wordCount": "23902字",
            "credits": "421,064",
            "latestUpdates": "2024-10-09 14:58:57"
        },
        {
            "author": "幻想空白",
            "title": "重启十一年",
            "url": "https://www.jjwxc.net/onebook.php?novelid=9180460",
            "genre": "近代现代-爱情",
            "status": "连载",
            "wordCount": "66362字",
            "credits": "276,801",
            "latestUpdates": "2024-10-10 07:00:00"
        },
        {
            "author": "葵哲",
            "title": "望安无间",
            "url": "https://www.jjwxc.net/onebook.php?novelid=9147848",
            "genre": "架空历史-仙侠",
            "status": "完结",
            "wordCount": "63880字",
            "credits": "238,325",
            "latestUpdates": "2024-09-28 11:11:40"
        },
        {
            "author": "百变小兔",
            "title": "重生成一条小蛇之后",
            "url": "https://www.jjwxc.net/onebook.php?novelid=9129457",
            "genre": "近代现代-爱情",
            "status": "连载",
            "wordCount": "33434字",
            "credits": "221,336",
            "latestUpdates": "2024-10-09 12:40:12"
        },
        {
            "author": "蓦下",
            "title": "重折茉莉花",
            "url": "https://www.jjwxc.net/onebook.php?novelid=9042886",
            "genre": "近代现代-爱情",
            "status": "连载",
            "wordCount": "48006字",
            "credits": "210,089",
            "latestUpdates": "2024-10-01 23:43:00"
        },
        {
            "author": "珩约",
            "title": "我那突然想开了的小姐",
            "url": "https://www.jjwxc.net/onebook.php?novelid=9170032",
            "genre": "架空历史-仙侠",
            "status": "连载",
            "wordCount": "27724字",
            "credits": "153,415",
            "latestUpdates": "2024-09-27 00:42:32"
        },
        {
            "author": "Partor",
            "title": "未见的盛夏",
            "url": "https://www.jjwxc.net/onebook.php?novelid=9107500",
            "genre": "近代现代-爱情",
            "status": "连载",
            "wordCount": "26447字",
            "credits": "143,477",
            "latestUpdates": "2024-08-21 19:00:00"
        },
        {
            "author": "三岁不大",
            "title": "再造盛唐",
            "url": "https://www.jjwxc.net/onebook.php?novelid=9161221",
            "genre": "架空历史-爱情",
            "status": "连载",
            "wordCount": "22870字",
            "credits": "142,363",
            "latestUpdates": "2024-09-23 20:10:29"
        },
        {
            "author": "夏长赢不emo",
            "title": "病弱殿下她不肯治病",
            "url": "https://www.jjwxc.net/onebook.php?novelid=9187215",
            "genre": "架空历史-剧情",
            "status": "连载",
            "wordCount": "19717字",
            "credits": "113,004",
            "latestUpdates": "2024-09-28 22:37:27"
        },
        {
            "author": "小南强",
            "title": "重生后师尊请自重",
            "url": "https://www.jjwxc.net/onebook.php?novelid=9152930",
            "genre": "古色古香-仙侠",
            "status": "连载",
            "wordCount": "20208字",
            "credits": "93,710",
            "latestUpdates": "2024-09-05 23:25:38"
        },
        {
            "author": "青棠小屋",
            "title": "扶摇直上",
            "url": "https://www.jjwxc.net/onebook.php?novelid=9066762",
            "genre": "近代现代-爱情",
            "status": "连载",
            "wordCount": "23296字",
            "credits": "88,817",
            "latestUpdates": "2024-08-20 10:02:19"
        },
        {
            "author": "辣辣辣辣",
            "title": "重生之师姐对我欲罢不能",
            "url": "https://www.jjwxc.net/onebook.php?novelid=9170390",
            "genre": "架空历史-仙侠",
            "status": "连载",
            "wordCount": "10215字",
            "credits": "82,474",
            "latestUpdates": "2024-09-12 20:40:11"
        },
        {
            "author": "凌晨四点海棠花未眠",
            "title": "不曾言说",
            "url": "https://www.jjwxc.net/onebook.php?novelid=9156699",
            "genre": "近代现代-爱情",
            "status": "连载",
            "wordCount": "12579字",
            "credits": "74,154",
            "latestUpdates": "2024-09-02 21:15:59"
        },
        {
            "author": "飞鸟易安",
            "title": "月下剑的誓言",
            "url": "https://www.jjwxc.net/onebook.php?novelid=9135527",
            "genre": "架空历史-传奇",
            "status": "连载",
            "wordCount": "17076字",
            "credits": "67,150",
            "latestUpdates": "2024-08-26 21:53:12"
        },
        {
            "author": "司眠眠",
            "title": "二十四桥明月夜",
            "url": "https://www.jjwxc.net/onebook.php?novelid=9068595",
            "genre": "架空历史-爱情",
            "status": "连载",
            "wordCount": "14794字",
            "credits": "64,524",
            "latestUpdates": "2024-08-07 16:25:07"
        },
        {
            "author": "阿南舒",
            "title": "投胎",
            "url": "https://www.jjwxc.net/onebook.php?novelid=9144264",
            "genre": "古色古香-奇幻",
            "status": "连载",
            "wordCount": "10143字",
            "credits": "55,535",
            "latestUpdates": "2024-10-10 21:25:01"
        },
        {
            "author": "鸾青台",
            "title": "我脑海里的月亮",
            "url": "https://www.jjwxc.net/onebook.php?novelid=9190084",
            "genre": "架空历史-仙侠",
            "status": "连载",
            "wordCount": "12713字",
            "credits": "43,468",
            "latestUpdates": "2024-10-04 05:40:17"
        },
        {
            "author": "乐见音",
            "title": "T  or  D",
            "url": "https://www.jjwxc.net/onebook.php?novelid=9079025",
            "genre": "近代现代-悬疑",
            "status": "连载",
            "wordCount": "10053字",
            "credits": "38,914",
            "latestUpdates": "2024-08-29 18:29:36"
        }
    ],
    "2024-10-11, 08:38:37 GMT+8"
]